{
	"info": {
		"_postman_id": "c298adf4-b59f-405d-b1bd-d151f7e1cbf6",
		"name": "FlaskAPItest",
		"schema": "https://schema.getpostman.com/json/collection/v2.1.0/collection.json"
	},
	"item": [
		{
			"name": "http://127.0.0.1:12345/predict",
			"request": {
				"method": "POST",
				"header": [],
				"body": {
					"mode": "raw",
					"raw": "\r\n{\r\n    \"x1\" : 100,\r\n    \"x2\" : 1\r\n}   \r\n",
					"options": {
						"raw": {
							"language": "json"
						}
					}
				},
				"url": {
					"raw": "http://127.0.0.1:5000/predict",
					"protocol": "http",
					"host": [
						"127",
						"0",
						"0",
						"1"
					],
					"port": "5000",
					"path": [
						"predict"
					]
				},
				"description": "Testing th Flask API with Postman\r\n"
			},
			"response": []
		},
		{
			"name": "Docker predict test",
			"request": {
				"method": "POST",
				"header": [],
				"body": {
					"mode": "raw",
					"raw": "\r\n{\r\n    \"x1\" : 12,\r\n    \"x2\" : 11\r\n}   \r\n",
					"options": {
						"raw": {
							"language": "json"
						}
					}
				},
				"url": {
					"raw": "localhost:5000/predict",
					"host": [
						"localhost"
					],
					"port": "5000",
					"path": [
						"predict"
					]
				},
				"description": "Testing th Flask API with Postman\r\n"
			},
			"response": []
		}
	]
}